{
  "type": "function",
  "function": {
    "name": "bash",
    "description": "Execute a bash command. For commands that may take more than 2 seconds (network requests, builds, package installs, recursive file searches, compilation), you MUST set run_in_background=true. When run_in_background is true, you will be notified automatically when the command completes — do NOT sleep, poll, read output files, or wait for the result. Continue with other work or respond to the user.",
    "parameters": {
      "type": "object",
      "properties": {
        "command": {
          "type": "string",
          "description": "The bash command to execute"
        },
        "run_in_background": {
          "type": "boolean",
          "description": "MUST be true for commands that may take more than 2 seconds: network requests (curl, wget), builds (cargo build, npm install, make), recursive searches on large directories, package management (pip, brew), and any command with unpredictable execution time. Defaults to false."
        },
        "timeout": {
          "type": "number",
          "description": "Timeout in milliseconds for synchronous commands. Defaults to 120000 (2 minutes)."
        }
      },
      "required": ["command"]
    }
  }
}
